gitflow/__init__.py
gitflow/branches.py
gitflow/core.py
gitflow/exceptions.py
gitflow/util.py
gitflow/bin/__init__.py
gitflow/bin/_init.py
nu_gitflow-1.0.0dev.dist-info/DESCRIPTION.rst
nu_gitflow-1.0.0dev.dist-info/entry_points.txt
nu_gitflow-1.0.0dev.dist-info/METADATA
nu_gitflow-1.0.0dev.dist-info/metadata.json
nu_gitflow-1.0.0dev.dist-info/RECORD
nu_gitflow-1.0.0dev.dist-info/top_level.txt
nu_gitflow-1.0.0dev.dist-info/WHEEL
tests/__init__.py
tests/gitflow/__init__.py
tests/gitflow/test_bin.py
tests/gitflow/test_branches.py
tests/gitflow/test_core.py
tests/helpers/__init__.py
tests/helpers/factory.py
tests/usecases/__init__.py
tests/usecases/test_creation.py
