Metadata-Version: 2.0
Name: nu-gitflow
Version: 1.0.0dev
Summary: Git extensions to provide high-level repository operations for Vincent Driessen's branching model.
Home-page: http://github.com/chassing/gitflow/
Author: Christian Assing, Hartmut Goebel, Vincent Driessen
Author-email: chris@ca-net.org
License: BSD
Platform: any
Classifier: Development Status :: 4 - Beta
Classifier: Environment :: Console
Classifier: Intended Audience :: Developers
Classifier: License :: OSI Approved :: BSD License
Classifier: Operating System :: OS Independent
Classifier: Operating System :: POSIX
Classifier: Operating System :: MacOS :: MacOS X
Classifier: Programming Language :: Python
Classifier: Programming Language :: Python :: 2.7
Classifier: Programming Language :: Python :: 3.4
Classifier: Topic :: Software Development :: Version Control
Requires-Dist: GitPython (>=1.0.1)
Requires-Dist: future
